lchemme/__init__.py
lchemme/callbacks.py
lchemme/cli.py
lchemme/datasets.py
lchemme/evaluation.py
lchemme/featurizing.py
lchemme/io.py
lchemme/pretraining.py
lchemme/tokenizing.py
lchemme-0.0.3.dist-info/LICENSE
lchemme-0.0.3.dist-info/METADATA
lchemme-0.0.3.dist-info/WHEEL
lchemme-0.0.3.dist-info/entry_points.txt
lchemme-0.0.3.dist-info/top_level.txt
lchemme-0.0.3.dist-info/RECORD
