Metadata-Version: 2.1
Name: lchemme
Version: 0.0.3
Summary: Training and applying large chemistry models for embeddings.
Author-email: Eachan Johnson <eachan.johnson@crick.ac.uk>
License: MIT License
Project-URL: Homepage, https://github.com/scbirlab/lchemme
Project-URL: Bug Tracker, https://github.com/scbirlab/lchemme/issues
Keywords: science,chemistry,machine learning,analysis,cheminformatics,large language models,ai
Classifier: Development Status :: 3 - Alpha
Classifier: Intended Audience :: Science/Research
Classifier: Topic :: Scientific/Engineering :: Chemistry
Classifier: License :: OSI Approved :: MIT License
Classifier: Programming Language :: Python :: 3.8
Classifier: Programming Language :: Python :: 3.9
Classifier: Programming Language :: Python :: 3.10
Classifier: Programming Language :: Python :: 3.11
Classifier: Programming Language :: Python :: 3.12
Classifier: Programming Language :: Python :: 3 :: Only
Requires-Python: >=3.8
License-File: LICENSE
Requires-Dist: carabiner-tools[mpl,pd]>=0.0.4
Requires-Dist: datasets>=3.1.0
Requires-Dist: openpyxl==3.1.0
Requires-Dist: pandas
Requires-Dist: schemist>=0.0.4.post1
Requires-Dist: tensorboard
Requires-Dist: tokenizers
Requires-Dist: transformers[torch]
Requires-Dist: umap-learn
